qcinf/__init__.py
qcinf/py.typed
qcinf/utils.py
qcinf/_backends/__init__.py
qcinf/_backends/openbabel.py
qcinf/_backends/qcutils.py
qcinf/_backends/rdkit.py
qcinf/_backends/utils.py
qcinf/algorithms/__init__.py
qcinf/algorithms/conversion.py
qcinf/algorithms/geometry.py
qcinf-0.2.0.dist-info/METADATA
qcinf-0.2.0.dist-info/WHEEL
qcinf-0.2.0.dist-info/RECORD
