Metadata-Version: 2.4
Name: qcinf
Version: 0.2.0
Summary: Cheminformatics algorithms and structure utilities using standardized qcio data structures.
Project-URL: Homepage, https://github.com/coltonbh/qcinf
Project-URL: Source, https://github.com/coltonbh/qcinf
Project-URL: Changelog, https://github.com/coltonbh/qcinf/blob/master/CHANGELOG.md
Project-URL: Bug Tracker, https://github.com/coltonbh/qcinf/issues
Project-URL: repository, https://github.com/coltonbh/qcinf
Author-email: Colton Hicks <github@coltonhicks.com>
Classifier: Development Status :: 4 - Beta
Classifier: Intended Audience :: Developers
Classifier: Intended Audience :: Science/Research
Classifier: License :: OSI Approved :: MIT License
Classifier: Natural Language :: English
Classifier: Programming Language :: Python :: 3.9
Classifier: Programming Language :: Python :: 3.10
Classifier: Programming Language :: Python :: 3.11
Classifier: Programming Language :: Python :: 3.12
Classifier: Programming Language :: Python :: 3.13
Classifier: Programming Language :: Python :: 3.14
Classifier: Topic :: Scientific/Engineering
Classifier: Topic :: Software Development :: Libraries
Requires-Python: >=3.10
Requires-Dist: pydantic!=2.0.1,!=2.1.0,~=2.0
Requires-Dist: qcconst>=0.2.1
Requires-Dist: qcio>=0.14.0
Requires-Dist: typing-extensions>=4.12.2
Provides-Extra: all
Requires-Dist: openbabel-wheel>=3.1.1.21; extra == 'all'
Requires-Dist: rdkit>=2024.9.6; extra == 'all'
Provides-Extra: openbabel
Provides-Extra: rdkit
Requires-Dist: rdkit>=2024.9.6; extra == 'rdkit'
